README.txt
setup.py
src/colorops/__init__.py
src/colorops.egg-info/PKG-INFO
src/colorops.egg-info/SOURCES.txt
src/colorops.egg-info/dependency_links.txt
src/colorops.egg-info/top_level.txt