Metadata-Version: 1.0
Name: colorops
Version: 0.1
Summary: Colorops converts between colorspaces, finds the best text color for your background, and can adjust hue, saturation, contrast and brightness.
Home-page: https://github.com/nathforge/colorops
Author: Nathan Reynolds
Author-email: email@nreynolds.co.uk
License: UNKNOWN
Platform: UNKNOWN
